hello_noo/__init__.py
hello_noo/friendly_greetings.py
hello_noo/greetings.py
hello_noo-0.0.3.dist-info/licenses/LICENSE
hello_noo-0.0.3.dist-info/METADATA
hello_noo-0.0.3.dist-info/WHEEL
hello_noo-0.0.3.dist-info/top_level.txt
hello_noo-0.0.3.dist-info/RECORD
