Metadata-Version: 2.4
Name: hello-NOO
Version: 0.0.3
Summary: A small personal example package
Author-email: NeonOrangeOrange <neonorangeorange@gmail.com>
License-Expression: MIT
Project-URL: Homepage, https://neonorangeorange.github.io/hello-NOO/
Project-URL: Documentation, https://neonorangeorange.github.io/hello-NOO/
Project-URL: Source, https://github.com/NeonOrangeOrange/hello-NOO
Project-URL: Issues, https://github.com/NeonOrangeOrange/hello-NOO/issues
Classifier: Development Status :: 2 - Pre-Alpha
Classifier: Programming Language :: Python :: 3
Classifier: Operating System :: OS Independent
License-File: LICENSE
Provides-Extra: dev
Requires-Dist: build; extra == "dev"
Requires-Dist: twine; extra == "dev"
Provides-Extra: docs
Requires-Dist: mkdocs; extra == "docs"
Dynamic: license-file
